bmusic/__init__.py
bmusic/affix.py
bmusic/anim.py
bmusic/midi.py
bmusic/proc/__init__.py
bmusic/proc/hammer.py
bmusic/proc/intensity.py
bmusic/proc/note.py
bmusic/proc/procedure.py
bmusic/proc/scheduling.py
bmusic/utils/__init__.py
bmusic/utils/interp.py
bmusic-0.1.2.dist-info/LICENSE
bmusic-0.1.2.dist-info/METADATA
bmusic-0.1.2.dist-info/WHEEL
bmusic-0.1.2.dist-info/top_level.txt
bmusic-0.1.2.dist-info/RECORD
