Metadata-Version: 2.1
Name: bmusic
Version: 0.1.2
Summary: Utilities for procedural music animation in Blender.
Home-page: https://github.com/phuang1024/bmusic
Author: Patrick Huang
Author-email: phuang1024@gmail.com
License: UNKNOWN
Platform: UNKNOWN
Classifier: Programming Language :: Python :: 3
Classifier: License :: OSI Approved :: GNU General Public License v3 or later (GPLv3+)
Classifier: Operating System :: OS Independent
License-File: LICENSE
Requires-Dist: mido
Requires-Dist: numpy
Requires-Dist: tqdm
